[{"operationId":"xpWWpvJbj1CR1rN24xcF2w","operationType":"callMicroflow","parameters":{"Token":["MxModelReflection.Token"]},"constants":{"MicroflowName":"MxModelReflection.Ch_FindReference"},"allowedUserRoleSets":[]},{"operationId":"K1XQU7WU90OopZ4V1/I2tg","operationType":"commit","parameters":{"Objects":["AnyObjectList"]},"constants":{},"allowedUserRoleSets":[]},{"operationId":"jm4LID3Jmky16PqbVKNKEQ","operationType":"retrieve","parameters":{},"constants":{"PageName":"MxModelReflection.MxObjectReference_View","WidgetName":"MxModelReflection.MxObjectReference_View.dataView1","UsedAssociations":[],"UsedAttributes":[],"EntityPath":"MxModelReflection.MxObjectReference"},"allowedUserRoleSets":[]},{"operationId":"c0rhr0dy2Emz5kh2OyRT3Q","operationType":"rollback","parameters":{"Objects":["AnyObjectList"]},"constants":{},"allowedUserRoleSets":[]},{"operationId":"T8JmNVNan06VWencOUibkw","operationType":"retrieve","parameters":{},"constants":{"PageName":"MxModelReflection.MxObjects_Overview","WidgetName":"MxModelReflection.MxObjects.templateGrid2","UsedAssociations":[],"UsedAttributes":[],"EntityPath":"MxModelReflection.Microflows"},"allowedUserRoleSets":[]},{"operationId":"ND9DZvjo/ku9BpnWcIWNxA","operationType":"commit","parameters":{"Objects":["AnyObjectList"]},"constants":{},"allowedUserRoleSets":[]},{"operationId":"ZedYK+xhOUu+PrQyBwga2w","operationType":"rollback","parameters":{"Objects":["AnyObjectList"]},"constants":{},"allowedUserRoleSets":[]},{"operationId":"8jVehc5lvUqlRlslzEfHgg","operationType":"rollback","parameters":{"Objects":["AnyObjectList"]},"constants":{},"allowedUserRoleSets":[]},{"operationId":"FoHTVLn9+0qcPeOXh+w+xg","operationType":"rollback","parameters":{"Objects":["AnyObjectList"]},"constants":{},"allowedUserRoleSets":[]},{"operationId":"YMa07tSFw1+T6ZOV7B8qBQ","operationType":"callMicroflow","parameters":{"AccountPasswordData":["Administration.AccountPasswordData"]},"constants":{"MicroflowName":"Administration.ChangePassword"},"allowedUserRoleSets":[["Administrator"]]},{"operationId":"o77hJgGGP0m3Ew37Ue2yzA","operationType":"retrieve","parameters":{},"constants":{"PageName":"MxModelReflection.Microflow_View","WidgetName":"MxModelReflection.Microflow_View.dataView1","UsedAssociations":["MxModelReflection.Microflows/MxModelReflection.Microflows_Output_Type/MxModelReflection.ValueType"],"UsedAttributes":[],"EntityPath":"MxModelReflection.Microflows"},"allowedUserRoleSets":[]},{"operationId":"d4WZXjx3wEKYHA00McNTwA","operationType":"commit","parameters":{"Objects":["AnyObjectList"]},"constants":{},"allowedUserRoleSets":[]},{"operationId":"yPZoIwCg9EyRg6lF9YxzhA","operationType":"rollback","parameters":{"Objects":["AnyObjectList"]},"constants":{},"allowedUserRoleSets":[]},{"operationId":"A2/ScxGi/l28lL88INtfPA","operationType":"callMicroflow","parameters":{"Token":["MxModelReflection.Token"]},"constants":{"MicroflowName":"MxModelReflection.MB_TestTokenPattern"},"allowedUserRoleSets":[]},{"operationId":"DtkPYS6qzUSTIBSUnhhDKA","operationType":"rollback","parameters":{"Objects":["AnyObjectList"]},"constants":{},"allowedUserRoleSets":[]},{"operationId":"/qgprdzXBUSlY+mBSypSbw","operationType":"rollback","parameters":{"Objects":["AnyObjectList"]},"constants":{},"allowedUserRoleSets":[]},{"operationId":"at+SMZ4k01+qrtgOhVHICw","operationType":"callMicroflow","parameters":{"Certificate":["Encryption.PGPCertificate"]},"constants":{"MicroflowName":"Encryption.MB_SaveCertificate"},"allowedUserRoleSets":[]},{"operationId":"mxw23bjzD1ijxaPYV5XgsQ","operationType":"callMicroflow","parameters":{"DbSizeEstimate":["MxModelReflection.DbSizeEstimate"]},"constants":{"MicroflowName":"MxModelReflection.OC_FindObjectType"},"allowedUserRoleSets":[]},{"operationId":"2ul1/Vd/O0WHhnwdMzZE9Q","operationType":"rollback","parameters":{"Objects":["AnyObjectList"]},"constants":{},"allowedUserRoleSets":[]},{"operationId":"aGeTDGTUvUqE50rMKCf2ww","operationType":"retrieve","parameters":{"CurrentObject":["Administration.Account"]},"constants":{"PageName":"Administration.Account_Overview","WidgetName":"Administration.Account_Overview.listView1","UsedAssociations":[],"UsedAttributes":[],"EntityPath":"System.UserRoles/System.UserRole"},"allowedUserRoleSets":[]},{"operationId":"D4LFsjLu+Eao54hrWNRjpw","operationType":"commit","parameters":{"Objects":["AnyObjectList"]},"constants":{},"allowedUserRoleSets":[]},{"operationId":"LD0EGmVcxESBwMOFyY632w","operationType":"retrieve","parameters":{"CurrentObject":["MxModelReflection.DbSizeEstimate"]},"constants":{"PageName":"MxModelReflection.DbSizeEstimate_NewEdit","WidgetName":"MxModelReflection.DbSizeEstimate.referenceSelector1","UsedAssociations":[],"UsedAttributes":["MxModelReflection.MxObjectType/MxModelReflection.MxObjectType.CompleteName"],"EntityPath":"MxModelReflection.DbSizeEstimate_MxObjectType/MxModelReflection.MxObjectType"},"allowedUserRoleSets":[]},{"operationId":"N+TIel9IP0OSQ36U/QqxTA","operationType":"commit","parameters":{"Objects":["AnyObjectList"]},"constants":{},"allowedUserRoleSets":[]},{"operationId":"mmZ4vySUXFe42EOtbs0+Kg","operationType":"callMicroflow","parameters":{"Token":["MxModelReflection.Token"]},"constants":{"MicroflowName":"MxModelReflection.Ch_Reference"},"allowedUserRoleSets":[]},{"operationId":"MrvtbT5u8Eiam0Q+P4ddBQ","operationType":"create","parameters":{},"constants":{"ObjectType":"MxModelReflection.DbSizeEstimate"},"allowedUserRoleSets":[]},{"operationId":"8ifCoP2q5Vq5d7XVN9Fk7w","operationType":"callMicroflow","parameters":{"AccountPasswordData":["Administration.AccountPasswordData"]},"constants":{"MicroflowName":"Administration.ChangeMyPassword"},"allowedUserRoleSets":[["Administrator"],["User"]]},{"operationId":"1FHolHrH3lWLPbet7LUFnA","operationType":"callMicroflow","parameters":{},"constants":{"MicroflowName":"MxModelReflection.IVK_SyncObjects"},"allowedUserRoleSets":[]},{"operationId":"jFclmIQlO1GYUiC1qgPnnA","operationType":"callMicroflow","parameters":{"MxObjectType":["MxModelReflection.MxObjectType"]},"constants":{"MicroflowName":"MxModelReflection.IVK_MxObjectTypeCommit"},"allowedUserRoleSets":[]},{"operationId":"KlugLDNU70uslh3wHfw+PQ","operationType":"commit","parameters":{"Objects":["AnyObjectList"]},"constants":{},"allowedUserRoleSets":[]},{"operationId":"xy5Lic3lokqPmT50GOiNiA","operationType":"rollback","parameters":{"Objects":["AnyObjectList"]},"constants":{},"allowedUserRoleSets":[]},{"operationId":"zv1/1IFPzUioW9duIO598w","operationType":"retrieve","parameters":{"CurrentObject":["MxModelReflection.Token"]},"constants":{"PageName":"MxModelReflection.Token_NewEdit","WidgetName":"MxModelReflection.Token.referenceSelector2","UsedAssociations":[],"UsedAttributes":["MxModelReflection.MxObjectType/MxModelReflection.MxObjectType.CompleteName"],"EntityPath":"MxModelReflection.Token_MxObjectType_Referenced/MxModelReflection.MxObjectType"},"allowedUserRoleSets":[]},{"operationId":"PauIYEzCwE+XY67sWSAfeA","operationType":"retrieve","parameters":{},"constants":{"PageName":"MainModule.Page","WidgetName":"MainModule.Page.listView3","UsedAssociations":[],"UsedAttributes":[],"XPath":"//MainModule.FacultatiBraila"},"allowedUserRoleSets":[]},{"operationId":"G41HIry6FVm5IpysmLshVQ","operationType":"callMicroflow","parameters":{"Token":["MxModelReflection.Token"]},"constants":{"MicroflowName":"MxModelReflection.Ch_ObjecttypeReference"},"allowedUserRoleSets":[]},{"operationId":"3DPKwB7GXUyfr22A9LCY/w","operationType":"rollback","parameters":{"Objects":["AnyObjectList"]},"constants":{},"allowedUserRoleSets":[]},{"operationId":"1aO3i5y0REKx7TBzUF1LyA","operationType":"retrieve","parameters":{},"constants":{"PageName":"Administration.Account_Overview","WidgetName":"Administration.Account_Overview.dataGrid21","UsedAssociations":[],"UsedAttributes":["Administration.Account/Administration.Account.FullName","Administration.Account/System.User.Name","Administration.Account/System.UserRoles/System.UserRole/System.UserRole.Name","Administration.Account/System.User.LastLogin","Administration.Account/System.User.Active","Administration.Account/System.User.WebServiceUser","Administration.Account/Administration.Account.IsLocalUser"],"XPath":"//Administration.Account[(System.UserRoles/System.UserRole/System.grantableRoles[reversed()]/System.UserRole/System.UserRoles = '[%CurrentUser%]' or not(System.UserRoles/System.UserRole)) and Name != empty]"},"allowedUserRoleSets":[]},{"operationId":"I4q7W+J+GEGbAjKHQZaD7w","operationType":"rollback","parameters":{"Objects":["AnyObjectList"]},"constants":{},"allowedUserRoleSets":[]},{"operationId":"XCbTslY8jEGpHp3In202Ug","operationType":"rollback","parameters":{"Objects":["AnyObjectList"]},"constants":{},"allowedUserRoleSets":[]},{"operationId":"SKw/kCkvikaOBucK0EikcQ","operationType":"retrieve","parameters":{},"constants":{"PageName":"Administration.Account_Edit","WidgetName":"Administration.Account_Edit.comboBox4","UsedAssociations":[],"UsedAttributes":["System.TimeZone/System.TimeZone.Description"],"XPath":"//System.TimeZone"},"allowedUserRoleSets":[]},{"operationId":"a+J/QesO9kq0SeMRsOmKPQ","operationType":"rollback","parameters":{"Objects":["AnyObjectList"]},"constants":{},"allowedUserRoleSets":[]},{"operationId":"epaR8tgyAEmOTTOlDy2XtA","operationType":"rollback","parameters":{"Objects":["AnyObjectList"]},"constants":{},"allowedUserRoleSets":[]},{"operationId":"FdXj+Asi0ECor/z/4zeM3g","operationType":"retrieve","parameters":{},"constants":{"PageName":"Administration.Account_New","WidgetName":"Administration.Account_New.comboBox1","UsedAssociations":[],"UsedAttributes":["System.UserRole/System.UserRole.Name"],"XPath":"//System.UserRole[System.grantableRoles[reversed()]/System.UserRole/System.UserRoles = '[%CurrentUser%]']"},"allowedUserRoleSets":[]},{"operationId":"unnAwuHXPEKiUBgace6X6w","operationType":"retrieve","parameters":{},"constants":{"PageName":"MxModelReflection.MxObjects_Overview","WidgetName":"MxModelReflection.MxObjects.templateGrid1","UsedAssociations":[],"UsedAttributes":[],"EntityPath":"MxModelReflection.MxObjectType"},"allowedUserRoleSets":[]},{"operationId":"tKNVo9nEaE+XVCG7y1d2iw","operationType":"rollback","parameters":{"Objects":["AnyObjectList"]},"constants":{},"allowedUserRoleSets":[]},{"operationId":"3OiFRN9uyFyrHkWOomeacA","operationType":"callMicroflow","parameters":{"Certificate_PrivateKey":["Encryption.PGPCertificate"]},"constants":{"MicroflowName":"Encryption.MB_GenerateCertificate"},"allowedUserRoleSets":[]},{"operationId":"+3U+PX8V4E6vGWNo4ws4Fw","operationType":"retrieveByMicroflow","parameters":{"MxObjectType":["MxModelReflection.MxObjectType"]},"constants":{"PageName":"MxModelReflection.MxObjects_Overview","WidgetName":"MxModelReflection.MxObjects.dataView2","UsedAssociations":[],"UsedAttributes":[],"MicroflowName":"MxModelReflection.DSO_InheritsFromContainer"},"allowedUserRoleSets":[]},{"operationId":"PACur+iQyEi0ctQOHOrbjA","operationType":"retrieve","parameters":{},"constants":{"PageName":"Administration.Account_New","WidgetName":"Administration.Account_New.comboBox3","UsedAssociations":[],"UsedAttributes":["System.Language/System.Language.Description"],"XPath":"//System.Language"},"allowedUserRoleSets":[]},{"operationId":"Q1VvzzntNUmgZ8oZuTNlVQ","operationType":"retrieve","parameters":{},"constants":{"PageName":"Atlas_Core.Atlas_TopBar","WidgetName":"Atlas_Core.LanguageSelectorWidget.languageSelector1","UsedAssociations":[],"UsedAttributes":["System.Language/System.Language.Description"],"XPath":"//System.Language"},"allowedUserRoleSets":[]},{"operationId":"tJLMZGdEHE2nR7OFPN+ZaA","operationType":"commit","parameters":{"Objects":["AnyObjectList"]},"constants":{},"allowedUserRoleSets":[]},{"operationId":"zC4ZCGfbgkW4PBlbOU5dvg","operationType":"delete","parameters":{"Objects":["[MxModelReflection.Token]"]},"constants":{},"allowedUserRoleSets":[]},{"operationId":"ZnEXwgTVU1mvcJjQ7IujmA","operationType":"callMicroflow","parameters":{"Token":["MxModelReflection.Token"]},"constants":{"MicroflowName":"MxModelReflection.Ch_FindMemberReference"},"allowedUserRoleSets":[]},{"operationId":"5bmEXSU+iEmPikS7ygAIUg","operationType":"rollback","parameters":{"Objects":["AnyObjectList"]},"constants":{},"allowedUserRoleSets":[]},{"operationId":"uAs904t1yUe6ReBzXVCqdw","operationType":"rollback","parameters":{"Objects":["AnyObjectList"]},"constants":{},"allowedUserRoleSets":[]},{"operationId":"1xnpYP5kN0GbWWYMJub1Pg","operationType":"retrieve","parameters":{"CurrentObject":["MxModelReflection.Token"]},"constants":{"PageName":"MxModelReflection.Token_NewEdit","WidgetName":"MxModelReflection.Token.referenceSelector3","UsedAssociations":[],"UsedAttributes":["MxModelReflection.MxObjectMember/MxModelReflection.MxObjectMember.AttributeName"],"EntityPath":"MxModelReflection.Token_MxObjectMember/MxModelReflection.MxObjectMember"},"allowedUserRoleSets":[]},{"operationId":"pJ4hezoeLkOJInNLn4Lewg","operationType":"rollback","parameters":{"Objects":["AnyObjectList"]},"constants":{},"allowedUserRoleSets":[]},{"operationId":"jnAmjLDGwkeUcZF5LAxQZQ","operationType":"retrieve","parameters":{},"constants":{"PageName":"MxModelReflection.Member_View","WidgetName":"MxModelReflection.Member.referenceSelector1","UsedAssociations":[],"UsedAttributes":["MxModelReflection.ValueType/MxModelReflection.ValueType.Name"],"XPath":"//MxModelReflection.ValueType"},"allowedUserRoleSets":[]},{"operationId":"janJqd7QeEOiXd8wp7zvDQ","operationType":"rollback","parameters":{"Objects":["AnyObjectList"]},"constants":{},"allowedUserRoleSets":[]},{"operationId":"yczJr63unEez3iWfyXA13w","operationType":"retrieve","parameters":{"CurrentObject":["MxModelReflection.Token"]},"constants":{"PageName":"MxModelReflection.Token_NewEdit","WidgetName":"MxModelReflection.Token.referenceSelector4","UsedAssociations":[],"UsedAttributes":["MxModelReflection.MxObjectMember/MxModelReflection.MxObjectMember.AttributeName"],"EntityPath":"MxModelReflection.Token_MxObjectMember/MxModelReflection.MxObjectMember"},"allowedUserRoleSets":[]},{"operationId":"TaxJqlIZdUWLm05IWnQZUw","operationType":"retrieve","parameters":{"CurrentObject":["MxModelReflection.Microflows"]},"constants":{"PageName":"MxModelReflection.MxObjects_Overview","WidgetName":"MxModelReflection.MxObjects.dataView3","UsedAssociations":["MxModelReflection.Microflows/MxModelReflection.Microflows_Output_Type/MxModelReflection.ValueType"],"UsedAttributes":[],"EntityPath":"MxModelReflection.Microflows"},"allowedUserRoleSets":[]},{"operationId":"q1HKF9u7ZkqvwEpRZ+XMAw","operationType":"retrieve","parameters":{},"constants":{"PageName":"MxModelReflection.MxObjects_Overview","WidgetName":"MxModelReflection.MxObjects.referenceSelector2","UsedAssociations":[],"UsedAttributes":["MxModelReflection.ValueType/MxModelReflection.ValueType.TypeEnum"],"XPath":"//MxModelReflection.ValueType"},"allowedUserRoleSets":[]},{"operationId":"ZiPTjqh/RFmlkrQfHFBy/Q","operationType":"callMicroflow","parameters":{"TestPattern":["MxModelReflection.TestPattern"]},"constants":{"MicroflowName":"MxModelReflection.MB_TestThePattern"},"allowedUserRoleSets":[]},{"operationId":"QhJvvnJynk+pnx6aAXbEhw","operationType":"retrieve","parameters":{},"constants":{"PageName":"Atlas_Core.Atlas_Default","WidgetName":"Atlas_Core.LanguageSelectorWidget.languageSelector1","UsedAssociations":[],"UsedAttributes":["System.Language/System.Language.Description"],"XPath":"//System.Language"},"allowedUserRoleSets":[]},{"operationId":"sqvB93vSylusGSaHoqLoRw","operationType":"callMicroflow","parameters":{"Token":["MxModelReflection.Token"]},"constants":{"MicroflowName":"MxModelReflection.Ch_FindObjectTypeReference"},"allowedUserRoleSets":[]},{"operationId":"NYa+b007qUeBHLXWpjIDsw","operationType":"retrieve","parameters":{"CurrentObject":["Administration.AccountPasswordData"]},"constants":{"PageName":"Administration.Account_New","WidgetName":"Administration.Account_New.dataView1","UsedAssociations":["Administration.Account/System.UserRoles/System.UserRole","Administration.Account/System.User_Language/System.Language","Administration.Account/System.User_TimeZone/System.TimeZone"],"UsedAttributes":[],"EntityPath":"Administration.AccountPasswordData_Account/Administration.Account"},"allowedUserRoleSets":[]},{"operationId":"MP++wCCbZkyc4gpAh12P8w","operationType":"rollback","parameters":{"Objects":["AnyObjectList"]},"constants":{},"allowedUserRoleSets":[]},{"operationId":"x1v5KLefgFi5gZj4pZEFPg","operationType":"callMicroflow","parameters":{"Account":["Administration.Account"]},"constants":{"MicroflowName":"Administration.ShowMyPasswordForm"},"allowedUserRoleSets":[["Administrator"],["User"]]},{"operationId":"24m829imv0Ss9GNTryF1Rg","operationType":"rollback","parameters":{"Objects":["AnyObjectList"]},"constants":{},"allowedUserRoleSets":[]},{"operationId":"XBGTnlEnX0KAbVugjoNuIg","operationType":"rollback","parameters":{"Objects":["AnyObjectList"]},"constants":{},"allowedUserRoleSets":[]},{"operationId":"5NuZ7PWFSV2uuUWgc7G5Yg","operationType":"callMicroflow","parameters":{"Token":["MxModelReflection.Token"]},"constants":{"MicroflowName":"MxModelReflection.Ch_FindMember"},"allowedUserRoleSets":[]},{"operationId":"piIuv3+ickK58bmjp2pemw","operationType":"retrieve","parameters":{},"constants":{"PageName":"MxModelReflection.MemberEnum_View","WidgetName":"MxModelReflection.MemberEnum_View.dataView1","UsedAssociations":["MxModelReflection.MxObjectEnum/MxModelReflection.MxObjectMember_Type/MxModelReflection.ValueType"],"UsedAttributes":[],"EntityPath":"MxModelReflection.MxObjectEnum"},"allowedUserRoleSets":[]},{"operationId":"X4FYi5Lz+kOdTzv5iUQ0WQ","operationType":"create","parameters":{},"constants":{"ObjectType":"Encryption.ExampleConfiguration"},"allowedUserRoleSets":[]},{"operationId":"MLUgc3hl306qmpNyYjr5XQ","operationType":"retrieveByMicroflow","parameters":{},"constants":{"PageName":"MxModelReflection.MxObjects_Overview","WidgetName":"MxModelReflection.MxObjects.listView1","UsedAssociations":[],"UsedAttributes":[],"MicroflowName":"MxModelReflection.DSL_Modules"},"allowedUserRoleSets":[]},{"operationId":"IYgz/bzaPE2bglZkSz+zmg","operationType":"rollback","parameters":{"Objects":["AnyObjectList"]},"constants":{},"allowedUserRoleSets":[]},{"operationId":"i8vHs23N5UqbRpA9hhlXGw","operationType":"retrieve","parameters":{},"constants":{"PageName":"Administration.Account_Overview","WidgetName":"Administration.Account_Overview.dataGrid21","UsedAssociations":[],"UsedAttributes":["System.UserRole/System.UserRole.Name"],"XPath":"//System.UserRole"},"allowedUserRoleSets":[]},{"operationId":"MxMR3e+HN1+GOpqty5e/fQ","operationType":"callMicroflow","parameters":{},"constants":{"MicroflowName":"System.ShowHomePage"},"allowedUserRoleSets":[["Administrator"],["User"]]},{"operationId":"bbITMmO9kk+XTdxxqIwONQ","operationType":"retrieve","parameters":{},"constants":{"PageName":"MxModelReflection.Member_View","WidgetName":"MxModelReflection.Member.referenceSelector2","UsedAssociations":[],"UsedAttributes":["MxModelReflection.ValueType/MxModelReflection.ValueType.TypeEnum"],"XPath":"//MxModelReflection.ValueType"},"allowedUserRoleSets":[]},{"operationId":"eYixiJqhrF+rTOfsOYHqTA","operationType":"callMicroflow","parameters":{},"constants":{"MicroflowName":"Encryption.MB_NewPrivateKey"},"allowedUserRoleSets":[]},{"operationId":"zSRUnd0OfE+h0q7Xkcr56A","operationType":"delete","parameters":{"Objects":["[System.Session]"]},"constants":{},"allowedUserRoleSets":[]},{"operationId":"8MPn8tNZr0+DdXEpcD7QYw","operationType":"rollback","parameters":{"Objects":["AnyObjectList"]},"constants":{},"allowedUserRoleSets":[]},{"operationId":"gCD/RFeZ/0OCcv8BHhOFVg","operationType":"commit","parameters":{"Objects":["AnyObjectList"]},"constants":{},"allowedUserRoleSets":[]},{"operationId":"G+MyriFESFm2k0PjwNIrPg","operationType":"callMicroflow","parameters":{},"constants":{"MicroflowName":"Encryption.MB_GenerateKeyShowPage"},"allowedUserRoleSets":[]},{"operationId":"L+bjznDWDkCm+DEA0GfBtA","operationType":"rollback","parameters":{"Objects":["AnyObjectList"]},"constants":{},"allowedUserRoleSets":[]},{"operationId":"5Iz0Vz58YF+cLjmRe2u29Q","operationType":"callMicroflow","parameters":{"Account":["Administration.Account"]},"constants":{"MicroflowName":"Administration.ShowPasswordForm"},"allowedUserRoleSets":[["Administrator"]]},{"operationId":"4E+o0W4pMEaCe/ZD7kYlVg","operationType":"retrieve","parameters":{},"constants":{"PageName":"MxModelReflection.Microflow_View","WidgetName":"MxModelReflection.Microflow.referenceSelector1","UsedAssociations":[],"UsedAttributes":["MxModelReflection.ValueType/MxModelReflection.ValueType.Name"],"XPath":"//MxModelReflection.ValueType"},"allowedUserRoleSets":[]},{"operationId":"b930IWCkR1imnCgAYd/hYA","operationType":"callMicroflow","parameters":{"ExampleConfiguration":["Encryption.ExampleConfiguration"]},"constants":{"MicroflowName":"Encryption.MB_SavePassword"},"allowedUserRoleSets":[]},{"operationId":"aS+benrML0KC+GvSoHtbFw","operationType":"rollback","parameters":{"Objects":["AnyObjectList"]},"constants":{},"allowedUserRoleSets":[]},{"operationId":"UqFlBSt6c1GjUk9rrmU3sA","operationType":"callMicroflow","parameters":{"Token":["MxModelReflection.Token"]},"constants":{"MicroflowName":"MxModelReflection.Ch_Member"},"allowedUserRoleSets":[]},{"operationId":"3cWMtkvcZFm8RFNQRGbVqg","operationType":"callMicroflow","parameters":{},"constants":{"MicroflowName":"Administration.NewAccount"},"allowedUserRoleSets":[["Administrator"]]},{"operationId":"ITQsUUnIg02pcfRfl4JsPQ","operationType":"rollback","parameters":{"Objects":["AnyObjectList"]},"constants":{},"allowedUserRoleSets":[]},{"operationId":"8et3BPq8N0KmXsJD+mU+Ag","operationType":"delete","parameters":{"Objects":["[MxModelReflection.DbSizeEstimate]"]},"constants":{},"allowedUserRoleSets":[]},{"operationId":"ODG/XN+LiEqbfQatv5eJ8A","operationType":"retrieve","parameters":{},"constants":{"PageName":"MxModelReflection.MemberEnum_View","WidgetName":"MxModelReflection.MemberEnum.referenceSelector2","UsedAssociations":[],"UsedAttributes":["MxModelReflection.ValueType/MxModelReflection.ValueType.TypeEnum"],"XPath":"//MxModelReflection.ValueType"},"allowedUserRoleSets":[]},{"operationId":"UtE59EaHw02cUOJuOVb/Yw","operationType":"retrieve","parameters":{},"constants":{"PageName":"Encryption.CertificateManagement","WidgetName":"Encryption.CertificateManagement.dataGrid21","UsedAssociations":[],"UsedAttributes":["Encryption.PGPCertificate/Encryption.PGPCertificate.Reference","Encryption.PGPCertificate/Encryption.PGPCertificate.EmailAddress","Encryption.PGPCertificate/Encryption.PGPCertificate.CertificateType","Encryption.PGPCertificate/System.FileDocument.Name"],"XPath":"//Encryption.PGPCertificate"},"allowedUserRoleSets":[]},{"operationId":"UyH6JX5/O0yNPUWr3dBgOg","operationType":"rollback","parameters":{"Objects":["AnyObjectList"]},"constants":{},"allowedUserRoleSets":[]},{"operationId":"gHvgIwqUlE+znIrCo773yQ","operationType":"retrieve","parameters":{},"constants":{"PageName":"Administration.RuntimeInstances","WidgetName":"Administration.RuntimeInstances.dataGrid21","UsedAssociations":[],"UsedAttributes":["System.XASInstance/System.XASInstance.XASId","System.XASInstance/System.XASInstance.createdDate","System.XASInstance/System.XASInstance.AllowedNumberOfConcurrentUsers","System.XASInstance/System.XASInstance.PartnerName","System.XASInstance/System.XASInstance.CustomerName"],"XPath":"//System.XASInstance"},"allowedUserRoleSets":[]},{"operationId":"VrvV9MeJGUKi1FUSdrDGEg","operationType":"rollback","parameters":{"Objects":["AnyObjectList"]},"constants":{},"allowedUserRoleSets":[]},{"operationId":"awfnfZQn+0GPUqNtkcciAg","operationType":"rollback","parameters":{"Objects":["AnyObjectList"]},"constants":{},"allowedUserRoleSets":[]},{"operationId":"2dxFWCIP6E2orj8RvHzIPQ","operationType":"retrieve","parameters":{},"constants":{"PageName":"Administration.Account_New","WidgetName":"Administration.Account_New.comboBox2","UsedAssociations":[],"UsedAttributes":["System.TimeZone/System.TimeZone.Description"],"XPath":"//System.TimeZone"},"allowedUserRoleSets":[]},{"operationId":"51phUtqj51iNuADUoP2GIg","operationType":"callMicroflow","parameters":{"Certificate":["Encryption.PGPCertificate"]},"constants":{"MicroflowName":"Encryption.MB_OpenCertificateDetails"},"allowedUserRoleSets":[]},{"operationId":"0y9gCf5Y1EykEBNL6Heh1w","operationType":"rollback","parameters":{"Objects":["AnyObjectList"]},"constants":{},"allowedUserRoleSets":[]},{"operationId":"UJi6Owr73VmZrv/FNKst2g","operationType":"callMicroflow","parameters":{},"constants":{"MicroflowName":"MxModelReflection.IVK_RecalculateSize"},"allowedUserRoleSets":[]},{"operationId":"N+wgVgDfk0qcoO3MWQC9tA","operationType":"retrieve","parameters":{},"constants":{"PageName":"Administration.ScheduledEvents","WidgetName":"Administration.ScheduledEvents.dataGrid21","UsedAssociations":[],"UsedAttributes":["System.ScheduledEventInformation/System.ScheduledEventInformation.Name","System.ScheduledEventInformation/System.ScheduledEventInformation.Description","System.ScheduledEventInformation/System.ScheduledEventInformation.StartTime","System.ScheduledEventInformation/System.ScheduledEventInformation.Status","System.ScheduledEventInformation/System.ScheduledEventInformation.EndTime"],"XPath":"//System.ScheduledEventInformation"},"allowedUserRoleSets":[]},{"operationId":"iEdkc0naiFamE+Mrx/SaZw","operationType":"callMicroflow","parameters":{"AccountPasswordData":["Administration.AccountPasswordData"]},"constants":{"MicroflowName":"Administration.SaveNewAccount"},"allowedUserRoleSets":[["Administrator"]]},{"operationId":"F21A5WOJHlyWHwB/Vc4Bqw","operationType":"callMicroflow","parameters":{"Selection":["MxModelReflection.MxObjectReference"],"MxObjectType":["MxModelReflection.MxObjectType"]},"constants":{"MicroflowName":"MxModelReflection.IVK_OpenReferencedMendixObject"},"allowedUserRoleSets":[]},{"operationId":"/cHU8iZqFUKNsxbx1fgM7A","operationType":"commit","parameters":{"Objects":["AnyObjectList"]},"constants":{},"allowedUserRoleSets":[]},{"operationId":"aNPj0QH/vlC4HXVKNQLEMg","operationType":"callMicroflow","parameters":{"Token":["MxModelReflection.Token"]},"constants":{"MicroflowName":"MxModelReflection.Ch_ObjectTypeStart"},"allowedUserRoleSets":[]},{"operationId":"LoW5OU1jyky9nfzPy6F43Q","operationType":"retrieve","parameters":{},"constants":{"PageName":"Encryption.ChangePasswordExample_Overview","WidgetName":"Encryption.ExampleConfigurations.dataGrid21","UsedAssociations":[],"UsedAttributes":["Encryption.ExampleConfiguration/Encryption.ExampleConfiguration.Title","Encryption.ExampleConfiguration/Encryption.ExampleConfiguration.Password"],"XPath":"//Encryption.ExampleConfiguration"},"allowedUserRoleSets":[]},{"operationId":"k/Qg0ZS6eU+NmQS6QeBagA","operationType":"rollback","parameters":{"Objects":["AnyObjectList"]},"constants":{},"allowedUserRoleSets":[]},{"operationId":"EfPcabTcTEeo/JcUqmLVpw","operationType":"rollback","parameters":{"Objects":["AnyObjectList"]},"constants":{},"allowedUserRoleSets":[]},{"operationId":"A+63S8REEk2ACJWMS+Sfjw","operationType":"retrieve","parameters":{"CurrentObject":["MxModelReflection.Token"]},"constants":{"PageName":"MxModelReflection.Token_NewEdit","WidgetName":"MxModelReflection.Token.referenceSelector1","UsedAssociations":[],"UsedAttributes":["MxModelReflection.MxObjectType/MxModelReflection.MxObjectType.CompleteName"],"EntityPath":"MxModelReflection.Token_MxObjectType_Start/MxModelReflection.MxObjectType"},"allowedUserRoleSets":[]},{"operationId":"ZWhPQAKibkKqtXPptwbSzg","operationType":"create","parameters":{},"constants":{"ObjectType":"MxModelReflection.Token"},"allowedUserRoleSets":[]},{"operationId":"ybGKvf6RNEig5UmdWwGZHw","operationType":"retrieve","parameters":{"CurrentObject":["Encryption.PGPCertificate"]},"constants":{"PageName":"Encryption.PrivateKey_NewEdit","WidgetName":"Encryption.PrivateKey_NewEdit.dataView2","UsedAssociations":[],"UsedAttributes":[],"EntityPath":"Encryption.SecretKey_PublicKey/Encryption.PGPCertificate"},"allowedUserRoleSets":[]},{"operationId":"JC7B0UXljU2VLZXjT3aD8g","operationType":"delete","parameters":{"Objects":["[Administration.Account]"]},"constants":{},"allowedUserRoleSets":[]},{"operationId":"fKLF5cSL6UmSo5Jvr1h2Zg","operationType":"retrieve","parameters":{},"constants":{"PageName":"MxModelReflection.MxObjects_Overview","WidgetName":"MxModelReflection.MxObjects.referenceSelector1","UsedAssociations":[],"UsedAttributes":["MxModelReflection.ValueType/MxModelReflection.ValueType.Name"],"XPath":"//MxModelReflection.ValueType"},"allowedUserRoleSets":[]},{"operationId":"p1Q5qtXzY1yAI1ozJ9O1Ew","operationType":"callMicroflow","parameters":{"ExampleConfiguration":["Encryption.ExampleConfiguration"]},"constants":{"MicroflowName":"Encryption.MB_ShowChangePassword"},"allowedUserRoleSets":[]},{"operationId":"yF6W9fAyEkyEr4OxR/M7Dg","operationType":"retrieve","parameters":{},"constants":{"PageName":"MxModelReflection.MxObject_Details","WidgetName":"MxModelReflection.MxObject_Details.dataView1","UsedAssociations":[],"UsedAttributes":[],"EntityPath":"MxModelReflection.MxObjectType"},"allowedUserRoleSets":[]},{"operationId":"S8r8nZL4k0O2e0YXqlTZ+w","operationType":"rollback","parameters":{"Objects":["AnyObjectList"]},"constants":{},"allowedUserRoleSets":[]},{"operationId":"UryP3RM4J0m+/xFYZlTmNA","operationType":"rollback","parameters":{"Objects":["AnyObjectList"]},"constants":{},"allowedUserRoleSets":[]},{"operationId":"DBHSNfj5vlOd+SJ3Ltl1RA","operationType":"callMicroflow","parameters":{},"constants":{"MicroflowName":"Encryption.MB_NewPubKey"},"allowedUserRoleSets":[]},{"operationId":"QbG3PD5XDEOtC2fdfDJvFg","operationType":"retrieve","parameters":{"CurrentObject":["MxModelReflection.MxObjectType"]},"constants":{"PageName":"MxModelReflection.MxObjects_Overview","WidgetName":"MxModelReflection.MxObjects.dataView1","UsedAssociations":[],"UsedAttributes":[],"EntityPath":"MxModelReflection.MxObjectType"},"allowedUserRoleSets":[]},{"operationId":"hszjDuOh/EmSTSCFMF0uwQ","operationType":"rollback","parameters":{"Objects":["AnyObjectList"]},"constants":{},"allowedUserRoleSets":[]},{"operationId":"OIekXjzKAUyi4oW+ytMRrw","operationType":"commit","parameters":{"Objects":["AnyObjectList"]},"constants":{},"allowedUserRoleSets":[]},{"operationId":"zapUZR9V7kyrJmU3+RBNpg","operationType":"retrieve","parameters":{"CurrentObject":["MxModelReflection.Token"]},"constants":{"PageName":"MxModelReflection.Token_NewEdit","WidgetName":"MxModelReflection.Token.referenceSelector5","UsedAssociations":[],"UsedAttributes":["MxModelReflection.MxObjectReference/MxModelReflection.MxObjectReference.CompleteName"],"EntityPath":"MxModelReflection.Token_MxObjectReference/MxModelReflection.MxObjectReference"},"allowedUserRoleSets":[]},{"operationId":"2VpRWicThkCTc72l/Tcing","operationType":"commit","parameters":{"Objects":["AnyObjectList"]},"constants":{},"allowedUserRoleSets":[]},{"operationId":"fzqqcQ1OX0aAmjZx5e0tzg","operationType":"retrieve","parameters":{},"constants":{"PageName":"Administration.MyAccount","WidgetName":"Administration.MyAccount.comboBox3","UsedAssociations":[],"UsedAttributes":["System.Language/System.Language.Description"],"XPath":"//System.Language"},"allowedUserRoleSets":[]},{"operationId":"fC6qnJZ/OEqC4oPWWzebyA","operationType":"rollback","parameters":{"Objects":["AnyObjectList"]},"constants":{},"allowedUserRoleSets":[]},{"operationId":"dOQx/Ty+Okm43/PbjIbF+Q","operationType":"create","parameters":{},"constants":{"ObjectType":"Encryption.ExampleConfiguration"},"allowedUserRoleSets":[]},{"operationId":"M6s+8qrUGE6dF31mOGJfTQ","operationType":"rollback","parameters":{"Objects":["AnyObjectList"]},"constants":{},"allowedUserRoleSets":[]},{"operationId":"ntqElNPE4kODWdTifZPIMA","operationType":"rollback","parameters":{"Objects":["AnyObjectList"]},"constants":{},"allowedUserRoleSets":[]},{"operationId":"+gUQcxkbH0eFzBCSjA4gkg","operationType":"rollback","parameters":{"Objects":["AnyObjectList"]},"constants":{},"allowedUserRoleSets":[]},{"operationId":"xT6iFsijeFyJ3FKSf9BPVQ","operationType":"callMicroflow","parameters":{},"constants":{"MicroflowName":"Administration.NewWebServiceAccount"},"allowedUserRoleSets":[["Administrator"]]},{"operationId":"kbg7sNSutV2LXN6ZzCFsKw","operationType":"callMicroflow","parameters":{"Module":["MxModelReflection.Module"]},"constants":{"MicroflowName":"MxModelReflection.IVK_ToggleModule"},"allowedUserRoleSets":[]},{"operationId":"xVesKoYSUk6cTRBnuJANRw","operationType":"retrieve","parameters":{},"constants":{"PageName":"MxModelReflection.MemberEnum_View","WidgetName":"MxModelReflection.MemberEnum.referenceSelector1","UsedAssociations":[],"UsedAttributes":["MxModelReflection.ValueType/MxModelReflection.ValueType.Name"],"XPath":"//MxModelReflection.ValueType"},"allowedUserRoleSets":[]},{"operationId":"XFLo9ZdeMEmIxgklnfBByg","operationType":"retrieve","parameters":{},"constants":{"PageName":"Encryption.SavePasswordExample_Overview","WidgetName":"Encryption.SavePasswordExample_Overview.dataGrid21","UsedAssociations":[],"UsedAttributes":["Encryption.ExampleConfiguration/Encryption.ExampleConfiguration.Title","Encryption.ExampleConfiguration/Encryption.ExampleConfiguration.Username","Encryption.ExampleConfiguration/Encryption.ExampleConfiguration.Password"],"XPath":"//Encryption.ExampleConfiguration"},"allowedUserRoleSets":[]},{"operationId":"ueZ0RS+da0+pO0w3HGLPPg","operationType":"rollback","parameters":{"Objects":["AnyObjectList"]},"constants":{},"allowedUserRoleSets":[]},{"operationId":"ho7fFZZhpkudlqIiZMliIQ","operationType":"commit","parameters":{"Objects":["AnyObjectList"]},"constants":{},"allowedUserRoleSets":[]},{"operationId":"ernwa1ZxjkGbucY/9sHlBw","operationType":"retrieve","parameters":{},"constants":{"PageName":"Administration.Account_Edit","WidgetName":"Administration.Account_Edit.comboBox2","UsedAssociations":[],"UsedAttributes":["System.UserRole/System.UserRole.Name"],"XPath":"//System.UserRole[System.grantableRoles[reversed()]/System.UserRole/System.UserRoles = '[%CurrentUser%]']"},"allowedUserRoleSets":[]},{"operationId":"qUEmgWG6x06n7mTXiPKcRA","operationType":"retrieve","parameters":{},"constants":{"PageName":"Administration.ActiveSessions","WidgetName":"Administration.ActiveSessions.dataGrid21","UsedAssociations":[],"UsedAttributes":["System.Session/System.Session_User/System.User/System.User.Name","System.Session/System.Session.LastActive"],"XPath":"//System.Session"},"allowedUserRoleSets":[]},{"operationId":"4yEGk1So7UeBMojFYsonoQ","operationType":"retrieve","parameters":{},"constants":{"PageName":"Administration.Account_Edit","WidgetName":"Administration.Account_Edit.comboBox3","UsedAssociations":[],"UsedAttributes":["System.Language/System.Language.Description"],"XPath":"//System.Language"},"allowedUserRoleSets":[]},{"operationId":"NpR4Ddv48Euy9B6N4VJFIQ","operationType":"create","parameters":{},"constants":{"ObjectType":"MainModule.FacultatiBraila"},"allowedUserRoleSets":[]},{"operationId":"qTq9dLz3SlKjjHxfuWhsrg","operationType":"callMicroflow","parameters":{"PasswordData":["Encryption.PasswordData"]},"constants":{"MicroflowName":"Encryption.MB_ChangePasswordSave"},"allowedUserRoleSets":[]}]